setup.py
futile/Figures.py
futile/Inputvars.py
futile/Time.py
futile/Utils.py
futile/YamlArgparse.py
futile/YamlIO.py
futile/__init__.py
pyfutile-1.9.3.dist-info/METADATA
pyfutile-1.9.3.dist-info/WHEEL
pyfutile-1.9.3.dist-info/licenses/COPYING
pyfutile-1.9.3.dist-info/RECORD
