Metadata-Version: 2.1
Name: pyFutile
Version: 1.9.3
Summary: Python utilities for the Futile library
Project-URL: Homepage, https://bigdft.org
Project-URL: Bug Tracker, https://gitlab.com/l_sim/bigdft-suite/-/issues
Author-email: Damien Caliste <Damien.Caliste@cea.fr>, Thierry Deutsch <Thierry.Deutsch@cea.fr>, Luigi Genovese <Luigi.Genovese@cea.fr>
License:                     GNU GENERAL PUBLIC LICENSE
License-File: COPYING
Classifier: License :: OSI Approved :: GNU General Public License v3 (GPLv3)
Classifier: Operating System :: OS Independent
Classifier: Programming Language :: Python :: 3
Requires-Python: >=3.6
Requires-Dist: numpy
Requires-Dist: pyyaml
